mxmncl_readtime-0.1.0.dist-info/licenses/license
readtime/__init__.py
readtime/core.py
mxmncl_readtime-0.1.0.dist-info/METADATA
mxmncl_readtime-0.1.0.dist-info/WHEEL
mxmncl_readtime-0.1.0.dist-info/top_level.txt
mxmncl_readtime-0.1.0.dist-info/RECORD
